topological_quantum_compiler-0.1.0.dist-info/licenses/LICENSE
tqc/__init__.py
tqc/_version.py
tqc/anyons.py
tqc/braids.py
tqc/cli.py
tqc/compiler.py
tqc/optimization.py
tqc/simulation.py
topological_quantum_compiler-0.1.0.dist-info/METADATA
topological_quantum_compiler-0.1.0.dist-info/WHEEL
topological_quantum_compiler-0.1.0.dist-info/entry_points.txt
topological_quantum_compiler-0.1.0.dist-info/top_level.txt
topological_quantum_compiler-0.1.0.dist-info/RECORD
