Metadata-Version: 2.4
Name: topological-quantum-compiler
Version: 0.1.0
Summary: A universal compiler for quantum computers based on topological principles and anyonic braiding
Home-page: https://github.com/krish567366/TQC
Author: Krishna Bajpai
Author-email: krishna@krishnabajpai.me
Project-URL: Bug Tracker, https://github.com/krish567366/TQC/issues
Project-URL: Documentation, https://krish567366.github.io/TQC
Project-URL: Source Code, https://github.com/krish567366/TQC
Keywords: quantum topological compiler anyons braids fault-tolerant
Classifier: Development Status :: 3 - Alpha
Classifier: Intended Audience :: Science/Research
Classifier: License :: OSI Approved :: MIT License
Classifier: Operating System :: OS Independent
Classifier: Programming Language :: Python :: 3
Classifier: Programming Language :: Python :: 3.10
Classifier: Programming Language :: Python :: 3.11
Classifier: Programming Language :: Python :: 3.12
Classifier: Programming Language :: Python :: 3.13
Classifier: Topic :: Scientific/Engineering :: Physics
Classifier: Topic :: Scientific/Engineering :: Mathematics
Requires-Python: >=3.10
License-File: LICENSE
Requires-Dist: numpy>=1.21.0
Requires-Dist: scipy>=1.9.0
Requires-Dist: networkx>=2.8
Requires-Dist: matplotlib>=3.5.0
Requires-Dist: qiskit>=0.40.0
Requires-Dist: sympy>=1.10
Requires-Dist: pydantic>=1.10.0
Provides-Extra: jax
Requires-Dist: jax[cpu]>=0.4.0; extra == "jax"
Requires-Dist: jaxlib>=0.4.0; extra == "jax"
Provides-Extra: simulation
Requires-Dist: jax[cpu]>=0.4.0; extra == "simulation"
Requires-Dist: jaxlib>=0.4.0; extra == "simulation"
Provides-Extra: dev
Requires-Dist: pytest>=7.4.0; extra == "dev"
Requires-Dist: pytest-cov>=4.1.0; extra == "dev"
Requires-Dist: mypy>=1.5.0; extra == "dev"
Requires-Dist: black>=23.7.0; extra == "dev"
Requires-Dist: isort>=5.12.0; extra == "dev"
Requires-Dist: flake8>=6.0.0; extra == "dev"
Requires-Dist: pre-commit>=3.3.0; extra == "dev"
Provides-Extra: docs
Requires-Dist: mkdocs-material>=9.2.0; extra == "docs"
Requires-Dist: mkdocstrings[python]>=0.22.0; extra == "docs"
Requires-Dist: mkdocs-git-revision-date-localized-plugin>=1.2.0; extra == "docs"
Provides-Extra: all
Requires-Dist: jax[cpu]>=0.4.0; extra == "all"
Requires-Dist: jaxlib>=0.4.0; extra == "all"
Requires-Dist: pytest>=7.4.0; extra == "all"
Requires-Dist: pytest-cov>=4.1.0; extra == "all"
Requires-Dist: mypy>=1.5.0; extra == "all"
Requires-Dist: black>=23.7.0; extra == "all"
Requires-Dist: isort>=5.12.0; extra == "all"
Requires-Dist: flake8>=6.0.0; extra == "all"
Requires-Dist: pre-commit>=3.3.0; extra == "all"
Requires-Dist: mkdocs-material>=9.2.0; extra == "all"
Requires-Dist: mkdocstrings[python]>=0.22.0; extra == "all"
Requires-Dist: mkdocs-git-revision-date-localized-plugin>=1.2.0; extra == "all"
Dynamic: author
Dynamic: author-email
Dynamic: classifier
Dynamic: description
Dynamic: description-content-type
Dynamic: home-page
Dynamic: keywords
Dynamic: license-file
Dynamic: project-url
Dynamic: provides-extra
Dynamic: requires-dist
Dynamic: requires-python
Dynamic: summary
